task1/rom.sv
module rom #(
    parameter ADDRESS_WIDTH = 8,
    DATA_WIDTH = 8
)(
    input logic clk,
    input logic [ADDRESS_WIDTH-1:0] addr,
    output logic [DATA_WIDTH-1:0] dout
);

    logic [DATA_WIDTH-1:0] rom_array [2**ADDRESS_WIDTH-1:0];

    initial begin
        $display("Loading rom.");
        $readmemh("sinerom.mem", rom_array);
    end;

    always_ff @(posedge clk)
        dout <= rom_array[addr];
endmodule

task2/counter.sv
module counter #(
    parameter WIDTH = 8
)(
    input logic clk,
    input logic rst,
    input logic en,
    input logic [WIDTH-1:0] incr,
    output logic [WIDTH-1:0] count
);

always_ff @(posedge clk)
    if (rst) count <= {WIDTH{1'b0}};
    else if(en)
        count <= count + incr;

endmodule

task1/sinegen.sv
module sinegen(
    input logic [7:0] incr,
    input logic rst, en, clk,
    output logic [7:0] dout
);

    logic [7:0] addr;

    counter u_counter(clk, rst, en, incr, addr);
    rom rom(clk, addr, dout);

endmodule

task1/sinegen.vcd
$version Generated by VerilatedVcd $end
$date Tue Nov  4 02:14:32 2025 $end
$timescale 1ps $end

 $scope module TOP $end
  $var wire  1 & clk $end
  $var wire  8 ' dout [7:0] $end
  $var wire  1 % en $end
  $var wire  8 # incr [7:0] $end
  $var wire  1 $ rst $end
  $scope module sinegen $end
   $var wire  8 ( addr [7:0] $end
   $var wire  1 & clk $end
   $var wire  8 ' dout [7:0] $end
   $var wire  1 % en $end
   $var wire  8 # incr [7:0] $end
   $var wire  1 $ rst $end
   $scope module rom $end
    $var wire 32 ) ADDRESS_WIDTH [31:0] $end
    $var wire 32 ) DATA_WIDTH [31:0] $end
    $var wire  8 ( addr [7:0] $end
    $var wire  1 & clk $end
    $var wire  8 ' dout [7:0] $end
   $upscope $end
   $scope module u_counter $end
    $var wire 32 ) WIDTH [31:0] $end
    $var wire  1 & clk $end
    $var wire  8 ( count [7:0] $end
    $var wire  1 % en $end
    $var wire  8 # incr [7:0] $end
    $var wire  1 $ rst $end
   $upscope $end
  $upscope $end
 $upscope $end
$enddefinitions $end


#0
b00000001 #
1$
0%
1&
b00000000 '
b00000000 (
b00000000000000000000000000001000 )
#1
0&
#2
1&
b11111110 '
#3
1%
0&
#4
1&
#5
0&
#6
1&
#7
0$
0&
#8
1&
b00000001 (
#9
0&
#10
1&
b11111101 '
b00000010 (
#11
0&
#12
1&
b00000011 (
#13
0&
#14
1&
b00000100 (
#15
0&
#16
1&
b00000101 (
#17
0&
#18
1&
b00000110 (
#19
0&
#20
1&
b11111100 '
b00000111 (
#21
0&
#22
1&
b00001000 (
#23
0&
#24
1&
b11111011 '
b00001001 (
#25
0&
#26
1&
b11111010 '
b00001010 (
#27
0&
#28
1&
b00001011 (
#29
0&
#30
1&
b11111001 '
b00001100 (
#31
0&
#32
1&
b11111000 '
b00001101 (
#33
0&
#34
1&
b11110111 '
b00001110 (
#35
0&
#36
1&
b11110110 '
b00001111 (
#37
0&
#38
1&
b11110101 '
b00010000 (
#39
0&
#40
1&
b11110100 '
b00010001 (
#41
0&
#42
1&
b11110011 '
b00010010 (
#43
0&
#44
1&
b11110001 '
b00010011 (
#45
0&
#46
1&
b11110000 '
b00010100 (
#47
0&
#48
1&
b11101111 '
b00010101 (
#49
0&
#50
1&
b11101101 '
b00010110 (
#51
0&
#52
1&
b11101011 '
b00010111 (
#53
0&
#54
1&
b11101010 '
b00011000 (
#55
0&
#56
1&
b11101000 '
b00011001 (
#57
0&
#58
1&
b11100110 '
b00011010 (
#59
0&
#60
1&
b11100101 '
b00011011 (
#61
0&
#62
1&
b11100011 '
b00011100 (
#63
0&
#64
1&
b11100001 '
b00011101 (
#65
0&
#66
1&
b11011111 '
b00011110 (
#67
0&
#68
1&
b11011101 '
b00011111 (
#69
0&
#70
1&
b11011010 '
b00100000 (
#71
0&
#72
1&
b11011000 '
b00100001 (
#73
0&
#74
1&
b11010110 '
b00100010 (
#75
0&
#76
1&
b11010100 '
b00100011 (
#77
0&
#78
1&
b11010001 '
b00100100 (
#79
0&
#80
1&
b11001111 '
b00100101 (
#81
0&
#82
1&
b11001101 '
b00100110 (
#83
0&
#84
1&
b11001010 '
b00100111 (
#85
0&
#86
1&
b11001000 '
b00101000 (
#87
0&
#88
1&
b11000101 '
b00101001 (
#89
0&
#90
1&
b11000010 '
b00101010 (
#91
0&
#92
1&
b11000000 '
b00101011 (
#93
0&
#94
1&
b10111101 '
b00101100 (
#95
0&
#96
1&
b10111010 '
b00101101 (
#97
0&
#98
1&
b10111000 '
b00101110 (
#99
0&
#100
1&
b10110101 '
b00101111 (
#101
0&
#102
1&
b10110010 '
b00110000 (
#103
0&
#104
1&
b10101111 '
b00110001 (
#105
0&
#106
1&
b10101100 '
b00110010 (
#107
0&
#108
1&
b10101001 '
b00110011 (
#109
0&
#110
1&
b10100110 '
b00110100 (
#111
0&
#112
1&
b10100011 '
b00110101 (
#113
0&
#114
1&
b10100000 '
b00110110 (
#115
0&
#116
1&
b10011101 '
b00110111 (
#117
0&
#118
1&
b10011010 '
b00111000 (
#119
0&
#120
1&
b10010111 '
b00111001 (
#121
0&
#122
1&
b10010100 '
b00111010 (
#123
0&
#124
1&
b10010001 '
b00111011 (
#125
0&
#126
1&
b10001110 '
b00111100 (
#127
0&
#128
1&
b10001011 '
b00111101 (
#129
0&
#130
1&
b10001000 '
b00111110 (
#131
0&
#132
1&
b10000101 '
b00111111 (
#133
0&
#134
1&
b10000010 '
b01000000 (
#135
0&
#136
1&
b01111110 '
b01000001 (
#137
0&
#138
1&
b01111011 '
b01000010 (
#139
0&
#140
1&
b01111000 '
b01000011 (
#141
0&
#142
1&
b01110101 '
b01000100 (
#143
0&
#144
1&
b01110010 '
b01000101 (
#145
0&
#146
1&
b01101111 '
b01000110 (
#147
0&
#148
1&
b01101100 '
b01000111 (
#149
0&
#150
1&
b01101001 '
b01001000 (
#151
0&
#152
1&
b01100110 '
b01001001 (
#153
0&
#154
1&
b01100011 '
b01001010 (
#155
0&
#156
1&
b01100000 '
b01001011 (
#157
0&
#158
1&
b01011101 '
b01001100 (
#159
0&
#160
1&
b01011010 '
b01001101 (
#161
0&
#162
1&
b01010111 '
b01001110 (
#163
0&
#164
1&
b01010100 '
b01001111 (
#165
0&
#166
1&
b01010001 '
b01010000 (
#167
0&
#168
1&
b01001110 '
b01010001 (
#169
0&
#170
1&
b01001011 '
b01010010 (
#171
0&
#172
1&
b01001000 '
b01010011 (
#173
0&
#174
1&
b01000101 '
b01010100 (
#175
0&
#176
1&
b01000011 '
b01010101 (
#177
0&
#178
1&
b01000000 '
b01010110 (
#179
0&
#180
1&
b00111101 '
b01010111 (
#181
0&
#182
1&
b00111011 '
b01011000 (
#183
0&
#184
1&
b00111000 '
b01011001 (
#185
0&
#186
1&
b00110101 '
b01011010 (
#187
0&
#188
1&
b00110011 '
b01011011 (
#189
0&
#190
1&
b00110000 '
b01011100 (
#191
0&
#192
1&
b00101110 '
b01011101 (
#193
0&
#194
1&
b00101100 '
b01011110 (
#195
0&
#196
1&
b00101001 '
b01011111 (
#197
0&
#198
1&
b00100111 '
b01100000 (
#199
0&
#200
1&
b00100101 '
b01100001 (
#201
0&
#202
1&
b00100011 '
b01100010 (
#203
0&
#204
1&
b00100000 '
b01100011 (
#205
0&
#206
1&
b00011110 '
b01100100 (
#207
0&
#208
1&
b00011100 '
b01100101 (
#209
0&
#210
1&
b00011010 '
b01100110 (
#211
0&
#212
1&
b00011000 '
b01100111 (
#213
0&
#214
1&
b00010111 '
b01101000 (
#215
0&
#216
1&
b00010101 '
b01101001 (
#217
0&
#218
1&
b00010011 '
b01101010 (
#219
0&
#220
1&
b00010010 '
b01101011 (
#221
0&
#222
1&
b00010000 '
b01101100 (
#223
0&
#224
1&
b00001110 '
b01101101 (
#225
0&
#226
1&
b00001101 '
b01101110 (
#227
0&
#228
1&
b00001100 '
b01101111 (
#229
0&
#230
1&
b00001010 '
b01110000 (
#231
0&
#232
1&
b00001001 '
b01110001 (
#233
0&
#234
1&
b00001000 '
b01110010 (
#235
0&
#236
1&
b00000111 '
b01110011 (
#237
0&
#238
1&
b00000110 '
b01110100 (
#239
0&
#240
1&
b00000101 '
b01110101 (
#241
0&
#242
1&
b00000100 '
b01110110 (
#243
0&
#244
1&
b00000011 '
b01110111 (
